freezegun-stubs/METADATA.toml
freezegun-stubs/__init__.pyi
freezegun-stubs/api.pyi
types_freezegun-1.1.9.dist-info/METADATA
types_freezegun-1.1.9.dist-info/WHEEL
types_freezegun-1.1.9.dist-info/top_level.txt
types_freezegun-1.1.9.dist-info/RECORD
